{
    "date": "2024-03-21",
    "amount": 3143917352,
    "shares": 60425000,
    "net": 52.03,
    "stocks": {
        "9983 JT": {
            "id": "9983 JT",
            "name": "FAST RETAILING CO LTD",
            "name_en": "Fast Retailing Co Ltd",
            "shares": 33800,
            "weight": 10.62
        },
        "8035 JT": {
            "id": "8035 JT",
            "name": "TOKYO ELECTRON LTD",
            "name_en": "Tokyo Electron Ltd",
            "shares": 33800,
            "weight": 8.91
        },
        "9984 JT": {
            "id": "9984 JT",
            "name": "SOFTBANK GROUP CORP",
            "name_en": "SoftBank Group Corp",
            "shares": 67500,
            "weight": 4.19
        },
        "6857 JT": {
            "id": "6857 JT",
            "name": "ADVANTEST CORP",
            "name_en": "Advantest Corp",
            "shares": 90000,
            "weight": 4.07
        },
        "4063 JT": {
            "id": "4063 JT",
            "name": "SHIN-ETSU CHEMICAL CO LTD",
            "name_en": "Shin-Etsu Chemical Co Ltd",
            "shares": 56300,
            "weight": 2.59
        },
        "9433 JT": {
            "id": "9433 JT",
            "name": "KDDI CORP",
            "name_en": "KDDI Corp",
            "shares": 67500,
            "weight": 2.05
        },
        "4543 JT": {
            "id": "4543 JT",
            "name": "TERUMO CORP",
            "name_en": "Terumo Corp",
            "shares": 45000,
            "weight": 1.72
        },
        "6762 JT": {
            "id": "6762 JT",
            "name": "TDK CORP",
            "name_en": "TDK Corp",
            "shares": 33800,
            "weight": 1.7
        },
        "6954 JT": {
            "id": "6954 JT",
            "name": "FANUC CORP",
            "name_en": "FANUC Corp",
            "shares": 56300,
            "weight": 1.65
        },
        "6367 JT": {
            "id": "6367 JT",
            "name": "DAIKIN INDUSTRIES LTD",
            "name_en": "Daikin Industries Ltd",
            "shares": 11300,
            "weight": 1.57
        },
        "6098 JT": {
            "id": "6098 JT",
            "name": "RECRUIT HOLDINGS CO LTD",
            "name_en": "Recruit Holdings Co Ltd",
            "shares": 33800,
            "weight": 1.5
        },
        "7203 JT": {
            "id": "7203 JT",
            "name": "TOYOTA MOTOR CORP",
            "name_en": "Toyota Motor Corp",
            "shares": 56300,
            "weight": 1.43
        },
        "4519 JT": {
            "id": "4519 JT",
            "name": "CHUGAI PHARMACEUTICAL CO LTD",
            "name_en": "Chugai Pharmaceutical Co Ltd",
            "shares": 33800,
            "weight": 1.38
        },
        "6920 JT": {
            "id": "6920 JT",
            "name": "LASERTEC CORP",
            "name_en": "Lasertec Corp",
            "shares": 4500,
            "weight": 1.3
        },
        "6971 JT": {
            "id": "6971 JT",
            "name": "KYOCERA CORP",
            "name_en": "Kyocera Corp",
            "shares": 90000,
            "weight": 1.28
        },
        "4568 JT": {
            "id": "4568 JT",
            "name": "DAIICHI SANKYO CO LTD",
            "name_en": "Daiichi Sankyo Co Ltd",
            "shares": 33800,
            "weight": 1.11
        },
        "6988 JT": {
            "id": "6988 JT",
            "name": "NITTO DENKO CORP",
            "name_en": "Nitto Denko Corp",
            "shares": 11300,
            "weight": 1.08
        },
        "6758 JT": {
            "id": "6758 JT",
            "name": "SONY GROUP CORP",
            "name_en": "Sony Group Corp",
            "shares": 11300,
            "weight": 1.02
        },
        "9613 JT": {
            "id": "9613 JT",
            "name": "NTT DATA GROUP CORP",
            "name_en": "NTT Data Group Corp",
            "shares": 56300,
            "weight": 0.96
        },
        "6902 JT": {
            "id": "6902 JT",
            "name": "DENSO CORP",
            "name_en": "Denso Corp",
            "shares": 45000,
            "weight": 0.88
        },
        "9735 JT": {
            "id": "9735 JT",
            "name": "SECOM CO LTD",
            "name_en": "Secom Co Ltd",
            "shares": 11300,
            "weight": 0.88
        },
        "7267 JT": {
            "id": "7267 JT",
            "name": "HONDA MOTOR CO LTD",
            "name_en": "Honda Motor Co Ltd",
            "shares": 67500,
            "weight": 0.86
        },
        "8058 JT": {
            "id": "8058 JT",
            "name": "MITSUBISHI CORP",
            "name_en": "Mitsubishi Corp",
            "shares": 33800,
            "weight": 0.8
        },
        "4901 JT": {
            "id": "4901 JT",
            "name": "FUJIFILM HOLDINGS CORP",
            "name_en": "FUJIFILM Holdings Corp",
            "shares": 11300,
            "weight": 0.79
        },
        "8015 JT": {
            "id": "8015 JT",
            "name": "TOYOTA TSUSHO CORP",
            "name_en": "Toyota Tsusho Corp",
            "shares": 11300,
            "weight": 0.79
        },
        "9766 JT": {
            "id": "9766 JT",
            "name": "KONAMI GROUP CORP",
            "name_en": "Konami Group Corp",
            "shares": 11300,
            "weight": 0.79
        },
        "2801 JT": {
            "id": "2801 JT",
            "name": "KIKKOMAN CORP",
            "name_en": "Kikkoman Corp",
            "shares": 11200,
            "weight": 0.75
        },
        "7741 JT": {
            "id": "7741 JT",
            "name": "HOYA CORP",
            "name_en": "Hoya Corp",
            "shares": 5600,
            "weight": 0.75
        },
        "7733 JT": {
            "id": "7733 JT",
            "name": "OLYMPUS CORP",
            "name_en": "Olympus Corp",
            "shares": 45000,
            "weight": 0.68
        },
        "7832 JT": {
            "id": "7832 JT",
            "name": "BANDAI NAMCO HOLDINGS INC",
            "name_en": "Bandai Namco Holdings Inc",
            "shares": 33800,
            "weight": 0.66
        },
        "6273 JT": {
            "id": "6273 JT",
            "name": "SMC CORP",
            "name_en": "SMC Corp",
            "shares": 1100,
            "weight": 0.65
        },
        "4503 JT": {
            "id": "4503 JT",
            "name": "ASTELLAS PHARMA INC",
            "name_en": "Astellas Pharma Inc",
            "shares": 56300,
            "weight": 0.63
        },
        "7974 JT": {
            "id": "7974 JT",
            "name": "NINTENDO CO LTD",
            "name_en": "Nintendo Co Ltd",
            "shares": 11300,
            "weight": 0.63
        },
        "4507 JT": {
            "id": "4507 JT",
            "name": "SHIONOGI & CO LTD",
            "name_en": "Shionogi & Co Ltd",
            "shares": 11300,
            "weight": 0.59
        },
        "4704 JT": {
            "id": "4704 JT",
            "name": "TREND MICRO INC",
            "name_en": "Trend Micro Inc/Japan",
            "shares": 11300,
            "weight": 0.58
        },
        "7735 JT": {
            "id": "7735 JT",
            "name": "SCREEN HOLDINGS CO LTD",
            "name_en": "SCREEN Holdings Co Ltd",
            "shares": 4500,
            "weight": 0.57
        },
        "8031 JT": {
            "id": "8031 JT",
            "name": "MITSUI & CO LTD",
            "name_en": "Mitsui & Co Ltd",
            "shares": 11300,
            "weight": 0.54
        },
        "8766 JT": {
            "id": "8766 JT",
            "name": "TOKIO MARINE HOLDINGS INC",
            "name_en": "Tokio Marine Holdings Inc",
            "shares": 16900,
            "weight": 0.54
        },
        "9843 JT": {
            "id": "9843 JT",
            "name": "NITORI HOLDINGS CO LTD",
            "name_en": "Nitori Holdings Co Ltd",
            "shares": 3400,
            "weight": 0.54
        },
        "6861 JT": {
            "id": "6861 JT",
            "name": "KEYENCE CORP",
            "name_en": "Keyence Corp",
            "shares": 1100,
            "weight": 0.53
        },
        "6981 JT": {
            "id": "6981 JT",
            "name": "MURATA MANUFACTURING CO LTD",
            "name_en": "Murata Manufacturing Co Ltd",
            "shares": 27000,
            "weight": 0.53
        },
        "7751 JT": {
            "id": "7751 JT",
            "name": "CANON INC",
            "name_en": "Canon Inc",
            "shares": 16900,
            "weight": 0.51
        },
        "3382 JT": {
            "id": "3382 JT",
            "name": "SEVEN & I HOLDINGS CO LTD",
            "name_en": "Seven & i Holdings Co Ltd",
            "shares": 33700,
            "weight": 0.5
        },
        "5108 JT": {
            "id": "5108 JT",
            "name": "BRIDGESTONE CORP",
            "name_en": "Bridgestone Corp",
            "shares": 11300,
            "weight": 0.5
        },
        "7269 JT": {
            "id": "7269 JT",
            "name": "SUZUKI MOTOR CORP",
            "name_en": "Suzuki Motor Corp",
            "shares": 11300,
            "weight": 0.5
        },
        "8001 JT": {
            "id": "8001 JT",
            "name": "ITOCHU CORP",
            "name_en": "ITOCHU Corp",
            "shares": 11300,
            "weight": 0.5
        },
        "4578 JT": {
            "id": "4578 JT",
            "name": "OTSUKA HOLDINGS CO LTD",
            "name_en": "Otsuka Holdings Co Ltd",
            "shares": 11300,
            "weight": 0.49
        },
        "6506 JT": {
            "id": "6506 JT",
            "name": "YASKAWA ELECTRIC CORP",
            "name_en": "Yaskawa Electric Corp",
            "shares": 11300,
            "weight": 0.49
        },
        "4523 JT": {
            "id": "4523 JT",
            "name": "EISAI CO LTD",
            "name_en": "Eisai Co Ltd",
            "shares": 11300,
            "weight": 0.48
        },
        "4021 JT": {
            "id": "4021 JT",
            "name": "NISSAN CHEMICAL CORP",
            "name_en": "Nissan Chemical Corp",
            "shares": 11300,
            "weight": 0.46
        },
        "4452 JT": {
            "id": "4452 JT",
            "name": "KAO CORP",
            "name_en": "Kao Corp",
            "shares": 11300,
            "weight": 0.43
        },
        "6645 JT": {
            "id": "6645 JT",
            "name": "OMRON CORP",
            "name_en": "Omron Corp",
            "shares": 11300,
            "weight": 0.43
        },
        "2502 JT": {
            "id": "2502 JT",
            "name": "ASAHI GROUP HOLDINGS LTD",
            "name_en": "Asahi Group Holdings Ltd",
            "shares": 11200,
            "weight": 0.41
        },
        "2802 JT": {
            "id": "2802 JT",
            "name": "AJINOMOTO CO INC",
            "name_en": "Ajinomoto Co Inc",
            "shares": 11200,
            "weight": 0.41
        },
        "3659 JT": {
            "id": "3659 JT",
            "name": "NEXON CO LTD",
            "name_en": "Nexon Co Ltd",
            "shares": 22500,
            "weight": 0.41
        },
        "6724 JT": {
            "id": "6724 JT",
            "name": "SEIKO EPSON CORP",
            "name_en": "Seiko Epson Corp",
            "shares": 22500,
            "weight": 0.4
        },
        "8830 JT": {
            "id": "8830 JT",
            "name": "SUMITOMO REALTY & DEVELOPMEN",
            "name_en": "Sumitomo Realty & Development Co Ltd",
            "shares": 11300,
            "weight": 0.4
        },
        "6594 JT": {
            "id": "6594 JT",
            "name": "NIDEC CORP",
            "name_en": "NIDEC CORP",
            "shares": 9000,
            "weight": 0.39
        },
        "2413 JT": {
            "id": "2413 JT",
            "name": "M3 INC",
            "name_en": "M3 Inc",
            "shares": 26900,
            "weight": 0.38
        },
        "4661 JT": {
            "id": "4661 JT",
            "name": "ORIENTAL LAND CO LTD",
            "name_en": "Oriental Land Co Ltd/Japan",
            "shares": 11300,
            "weight": 0.38
        },
        "8801 JT": {
            "id": "8801 JT",
            "name": "MITSUI FUDOSAN CO LTD",
            "name_en": "Mitsui Fudosan Co Ltd",
            "shares": 11300,
            "weight": 0.37
        },
        "6301 JT": {
            "id": "6301 JT",
            "name": "KOMATSU LTD",
            "name_en": "Komatsu Ltd",
            "shares": 11300,
            "weight": 0.35
        },
        "6305 JT": {
            "id": "6305 JT",
            "name": "HITACHI CONSTRUCTION MACHINE",
            "name_en": "Hitachi Construction Machinery Co Ltd",
            "shares": 11300,
            "weight": 0.35
        },
        "1925 JT": {
            "id": "1925 JT",
            "name": "DAIWA HOUSE INDUSTRY CO LTD",
            "name_en": "Daiwa House Industry Co Ltd",
            "shares": 11200,
            "weight": 0.34
        },
        "4502 JT": {
            "id": "4502 JT",
            "name": "TAKEDA PHARMACEUTICAL CO LTD",
            "name_en": "Takeda Pharmaceutical Co Ltd",
            "shares": 11300,
            "weight": 0.33
        },
        "4324 JT": {
            "id": "4324 JT",
            "name": "DENTSU GROUP INC",
            "name_en": "Dentsu Group Inc",
            "shares": 11300,
            "weight": 0.32
        },
        "4911 JT": {
            "id": "4911 JT",
            "name": "SHISEIDO CO LTD",
            "name_en": "Shiseido Co Ltd",
            "shares": 11300,
            "weight": 0.32
        },
        "7272 JT": {
            "id": "7272 JT",
            "name": "YAMAHA MOTOR CO LTD",
            "name_en": "Yamaha Motor Co Ltd",
            "shares": 33800,
            "weight": 0.32
        },
        "8697 JT": {
            "id": "8697 JT",
            "name": "JAPAN EXCHANGE GROUP INC",
            "name_en": "Japan Exchange Group Inc",
            "shares": 11300,
            "weight": 0.31
        },
        "2914 JT": {
            "id": "2914 JT",
            "name": "JAPAN TOBACCO INC",
            "name_en": "Japan Tobacco Inc",
            "shares": 11200,
            "weight": 0.3
        },
        "8053 JT": {
            "id": "8053 JT",
            "name": "SUMITOMO CORP",
            "name_en": "Sumitomo Corp",
            "shares": 11300,
            "weight": 0.28
        },
        "1721 JT": {
            "id": "1721 JT",
            "name": "COMSYS HOLDINGS CORP",
            "name_en": "COMSYS Holdings Corp",
            "shares": 11200,
            "weight": 0.27
        },
        "6841 JT": {
            "id": "6841 JT",
            "name": "YOKOGAWA ELECTRIC CORP",
            "name_en": "Yokogawa Electric Corp",
            "shares": 11300,
            "weight": 0.27
        },
        "6976 JT": {
            "id": "6976 JT",
            "name": "TAIYO YUDEN CO LTD",
            "name_en": "Taiyo Yuden Co Ltd",
            "shares": 11300,
            "weight": 0.27
        },
        "8267 JT": {
            "id": "8267 JT",
            "name": "AEON CO LTD",
            "name_en": "Aeon Co Ltd",
            "shares": 11300,
            "weight": 0.27
        },
        "1928 JT": {
            "id": "1928 JT",
            "name": "SEKISUI HOUSE LTD",
            "name_en": "Sekisui House Ltd",
            "shares": 11200,
            "weight": 0.26
        },
        "7270 JT": {
            "id": "7270 JT",
            "name": "SUBARU CORP",
            "name_en": "Subaru Corp",
            "shares": 11300,
            "weight": 0.26
        },
        "8591 JT": {
            "id": "8591 JT",
            "name": "ORIX CORP",
            "name_en": "ORIX Corp",
            "shares": 11300,
            "weight": 0.26
        },
        "7951 JT": {
            "id": "7951 JT",
            "name": "YAMAHA CORP",
            "name_en": "Yamaha Corp",
            "shares": 11300,
            "weight": 0.25
        },
        "8253 JT": {
            "id": "8253 JT",
            "name": "CREDIT SAISON CO LTD",
            "name_en": "Credit Saison Co Ltd",
            "shares": 11300,
            "weight": 0.25
        },
        "9009 JT": {
            "id": "9009 JT",
            "name": "KEISEI ELECTRIC RAILWAY CO",
            "name_en": "Keisei Electric Railway Co Ltd",
            "shares": 5600,
            "weight": 0.24
        },
        "6479 JT": {
            "id": "6479 JT",
            "name": "MINEBEA MITSUMI INC",
            "name_en": "MINEBEA MITSUMI Inc",
            "shares": 11300,
            "weight": 0.23
        },
        "4151 JT": {
            "id": "4151 JT",
            "name": "KYOWA KIRIN CO LTD",
            "name_en": "Kyowa Kirin Co Ltd",
            "shares": 11300,
            "weight": 0.22
        },
        "9201 JT": {
            "id": "9201 JT",
            "name": "JAPAN AIRLINES CO LTD",
            "name_en": "Japan Airlines Co Ltd",
            "shares": 11300,
            "weight": 0.22
        },
        "6501 JT": {
            "id": "6501 JT",
            "name": "HITACHI LTD",
            "name_en": "Hitachi Ltd",
            "shares": 2300,
            "weight": 0.21
        },
        "8802 JT": {
            "id": "8802 JT",
            "name": "MITSUBISHI ESTATE CO LTD",
            "name_en": "Mitsubishi Estate Co Ltd",
            "shares": 11300,
            "weight": 0.21
        },
        "6361 JT": {
            "id": "6361 JT",
            "name": "EBARA CORP",
            "name_en": "Ebara Corp",
            "shares": 2300,
            "weight": 0.2
        },
        "6723 JT": {
            "id": "6723 JT",
            "name": "RENESAS ELECTRONICS CORP",
            "name_en": "Renesas Electronics Corp",
            "shares": 11300,
            "weight": 0.2
        },
        "8002 JT": {
            "id": "8002 JT",
            "name": "MARUBENI CORP",
            "name_en": "Marubeni Corp",
            "shares": 11300,
            "weight": 0.2
        },
        "2282 JT": {
            "id": "2282 JT",
            "name": "NH FOODS LTD",
            "name_en": "NH Foods Ltd",
            "shares": 5500,
            "weight": 0.19
        },
        "6503 JT": {
            "id": "6503 JT",
            "name": "MITSUBISHI ELECTRIC CORP",
            "name_en": "Mitsubishi Electric Corp",
            "shares": 11300,
            "weight": 0.19
        },
        "6702 JT": {
            "id": "6702 JT",
            "name": "FUJITSU LIMITED",
            "name_en": "Fujitsu Ltd",
            "shares": 1100,
            "weight": 0.19
        },
        "8252 JT": {
            "id": "8252 JT",
            "name": "MARUI GROUP CO LTD",
            "name_en": "Marui Group Co Ltd",
            "shares": 11300,
            "weight": 0.19
        },
        "3099 JT": {
            "id": "3099 JT",
            "name": "ISETAN MITSUKOSHI HOLDINGS L",
            "name_en": "Isetan Mitsukoshi Holdings Ltd",
            "shares": 11200,
            "weight": 0.18
        },
        "5802 JT": {
            "id": "5802 JT",
            "name": "SUMITOMO ELECTRIC INDUSTRIES",
            "name_en": "Sumitomo Electric Industries Ltd",
            "shares": 11300,
            "weight": 0.18
        },
        "6326 JT": {
            "id": "6326 JT",
            "name": "KUBOTA CORP",
            "name_en": "Kubota Corp",
            "shares": 11300,
            "weight": 0.18
        },
        "7912 JT": {
            "id": "7912 JT",
            "name": "DAI NIPPON PRINTING CO LTD",
            "name_en": "Dai Nippon Printing Co Ltd",
            "shares": 5600,
            "weight": 0.18
        },
        "8725 JT": {
            "id": "8725 JT",
            "name": "MS&AD INSURANCE GROUP HOLDIN",
            "name_en": "MS&AD Insurance Group Holdings Inc",
            "shares": 3400,
            "weight": 0.18
        },
        "9301 JT": {
            "id": "9301 JT",
            "name": "MITSUBISHI LOGISTICS CORP",
            "name_en": "Mitsubishi Logistics Corp",
            "shares": 5600,
            "weight": 0.18
        },
        "2002 JT": {
            "id": "2002 JT",
            "name": "NISSHIN SEIFUN GROUP INC",
            "name_en": "Nisshin Seifun Group Inc",
            "shares": 11200,
            "weight": 0.17
        },
        "5713 JT": {
            "id": "5713 JT",
            "name": "SUMITOMO METAL MINING CO LTD",
            "name_en": "Sumitomo Metal Mining Co Ltd",
            "shares": 5600,
            "weight": 0.17
        },
        "9064 JT": {
            "id": "9064 JT",
            "name": "YAMATO HOLDINGS CO LTD",
            "name_en": "Yamato Holdings Co Ltd",
            "shares": 11300,
            "weight": 0.17
        },
        "2503 JT": {
            "id": "2503 JT",
            "name": "KIRIN HOLDINGS CO LTD",
            "name_en": "Kirin Holdings Co Ltd",
            "shares": 11200,
            "weight": 0.16
        },
        "5019 JT": {
            "id": "5019 JT",
            "name": "IDEMITSU KOSAN CO LTD",
            "name_en": "Idemitsu Kosan Co Ltd",
            "shares": 22500,
            "weight": 0.16
        },
        "5332 JT": {
            "id": "5332 JT",
            "name": "TOTO LTD",
            "name_en": "TOTO Ltd",
            "shares": 5600,
            "weight": 0.16
        },
        "5803 JT": {
            "id": "5803 JT",
            "name": "FUJIKURA LTD",
            "name_en": "Fujikura Ltd",
            "shares": 11300,
            "weight": 0.16
        },
        "2871 JT": {
            "id": "2871 JT",
            "name": "NICHIREI CORP",
            "name_en": "Nichirei Corp",
            "shares": 5500,
            "weight": 0.15
        },
        "4385 JT": {
            "id": "4385 JT",
            "name": "MERCARI INC",
            "name_en": "Mercari Inc",
            "shares": 11300,
            "weight": 0.15
        },
        "5101 JT": {
            "id": "5101 JT",
            "name": "YOKOHAMA RUBBER CO LTD",
            "name_en": "Yokohama Rubber Co Ltd/The",
            "shares": 5600,
            "weight": 0.15
        },
        "5333 JT": {
            "id": "5333 JT",
            "name": "NGK INSULATORS LTD",
            "name_en": "NGK Insulators Ltd",
            "shares": 11300,
            "weight": 0.15
        },
        "6504 JT": {
            "id": "6504 JT",
            "name": "FUJI ELECTRIC CO LTD",
            "name_en": "Fuji Electric Co Ltd",
            "shares": 2300,
            "weight": 0.15
        },
        "8630 JT": {
            "id": "8630 JT",
            "name": "SOMPO HOLDINGS INC",
            "name_en": "Sompo Holdings Inc",
            "shares": 2300,
            "weight": 0.15
        },
        "9022 JT": {
            "id": "9022 JT",
            "name": "CENTRAL JAPAN RAILWAY CO",
            "name_en": "Central Japan Railway Co",
            "shares": 5600,
            "weight": 0.15
        },
        "9434 JT": {
            "id": "9434 JT",
            "name": "SOFTBANK CORP",
            "name_en": "SoftBank Corp",
            "shares": 11300,
            "weight": 0.15
        },
        "1802 JT": {
            "id": "1802 JT",
            "name": "OBAYASHI CORP",
            "name_en": "Obayashi Corp",
            "shares": 11200,
            "weight": 0.14
        },
        "6113 JT": {
            "id": "6113 JT",
            "name": "AMADA CO LTD",
            "name_en": "Amada Co Ltd",
            "shares": 11300,
            "weight": 0.14
        },
        "7911 JT": {
            "id": "7911 JT",
            "name": "TOPPAN HOLDINGS INC",
            "name_en": "TOPPAN Holdings Inc",
            "shares": 5600,
            "weight": 0.14
        },
        "9107 JT": {
            "id": "9107 JT",
            "name": "KAWASAKI KISEN KAISHA LTD",
            "name_en": "Kawasaki Kisen Kaisha Ltd",
            "shares": 3400,
            "weight": 0.14
        },
        "9432 JT": {
            "id": "9432 JT",
            "name": "NIPPON TELEGRAPH & TELEPHONE",
            "name_en": "Nippon Telegraph & Telephone Corp",
            "shares": 112500,
            "weight": 0.14
        },
        "1812 JT": {
            "id": "1812 JT",
            "name": "KAJIMA CORP",
            "name_en": "Kajima Corp",
            "shares": 5500,
            "weight": 0.12
        },
        "3405 JT": {
            "id": "3405 JT",
            "name": "KURARAY CO LTD",
            "name_en": "Kuraray Co Ltd",
            "shares": 11300,
            "weight": 0.12
        },
        "5831 JT": {
            "id": "5831 JT",
            "name": "SHIZUOKA FINANCIAL GROUP INC",
            "name_en": "Shizuoka Financial Group Inc",
            "shares": 11300,
            "weight": 0.12
        },
        "6178 JT": {
            "id": "6178 JT",
            "name": "JAPAN POST HOLDINGS CO LTD",
            "name_en": "Japan Post Holdings Co Ltd",
            "shares": 11300,
            "weight": 0.12
        },
        "7731 JT": {
            "id": "7731 JT",
            "name": "NIKON CORP",
            "name_en": "Nikon Corp",
            "shares": 11300,
            "weight": 0.12
        },
        "8306 JT": {
            "id": "8306 JT",
            "name": "MITSUBISHI UFJ FINANCIAL GRO",
            "name_en": "Mitsubishi UFJ Financial Group Inc",
            "shares": 11300,
            "weight": 0.12
        },
        "1963 JT": {
            "id": "1963 JT",
            "name": "JGC HOLDINGS CORP",
            "name_en": "JGC Holdings Corp",
            "shares": 11200,
            "weight": 0.11
        },
        "6103 JT": {
            "id": "6103 JT",
            "name": "OKUMA CORP",
            "name_en": "OKUMA Corp",
            "shares": 2300,
            "weight": 0.11
        },
        "6473 JT": {
            "id": "6473 JT",
            "name": "JTEKT CORP",
            "name_en": "JTEKT Corp",
            "shares": 11300,
            "weight": 0.11
        },
        "6752 JT": {
            "id": "6752 JT",
            "name": "PANASONIC HOLDINGS CORP",
            "name_en": "Panasonic Holdings Corp",
            "shares": 11300,
            "weight": 0.11
        },
        "9104 JT": {
            "id": "9104 JT",
            "name": "MITSUI OSK LINES LTD",
            "name_en": "Mitsui OSK Lines Ltd",
            "shares": 3400,
            "weight": 0.11
        },
        "2269 JT": {
            "id": "2269 JT",
            "name": "MEIJI HOLDINGS CO LTD",
            "name_en": "MEIJI Holdings Co Ltd",
            "shares": 4400,
            "weight": 0.1
        },
        "6952 JT": {
            "id": "6952 JT",
            "name": "CASIO COMPUTER CO LTD",
            "name_en": "Casio Computer Co Ltd",
            "shares": 11300,
            "weight": 0.1
        },
        "7011 JT": {
            "id": "7011 JT",
            "name": "MITSUBISHI HEAVY INDUSTRIES",
            "name_en": "Mitsubishi Heavy Industries Ltd",
            "shares": 1100,
            "weight": 0.1
        },
        "7752 JT": {
            "id": "7752 JT",
            "name": "RICOH CO LTD",
            "name_en": "Ricoh Co Ltd",
            "shares": 11300,
            "weight": 0.1
        },
        "8331 JT": {
            "id": "8331 JT",
            "name": "CHIBA BANK LTD/THE",
            "name_en": "Chiba Bank Ltd/The",
            "shares": 11300,
            "weight": 0.1
        },
        "9101 JT": {
            "id": "9101 JT",
            "name": "NIPPON YUSEN KK",
            "name_en": "Nippon Yusen KK",
            "shares": 3400,
            "weight": 0.1
        },
        "1801 JT": {
            "id": "1801 JT",
            "name": "TAISEI CORP",
            "name_en": "Taisei Corp",
            "shares": 2200,
            "weight": 0.09
        },
        "2501 JT": {
            "id": "2501 JT",
            "name": "SAPPORO HOLDINGS LTD",
            "name_en": "Sapporo Holdings Ltd",
            "shares": 2200,
            "weight": 0.09
        },
        "3289 JT": {
            "id": "3289 JT",
            "name": "TOKYU FUDOSAN HOLDINGS CORP",
            "name_en": "Tokyu Fudosan Holdings Corp",
            "shares": 11200,
            "weight": 0.09
        },
        "3407 JT": {
            "id": "3407 JT",
            "name": "ASAHI KASEI CORP",
            "name_en": "Asahi Kasei Corp",
            "shares": 11300,
            "weight": 0.09
        },
        "5201 JT": {
            "id": "5201 JT",
            "name": "AGC INC",
            "name_en": "AGC Inc",
            "shares": 2300,
            "weight": 0.09
        },
        "5214 JT": {
            "id": "5214 JT",
            "name": "NIPPON ELECTRIC GLASS CO LTD",
            "name_en": "Nippon Electric Glass Co Ltd",
            "shares": 3400,
            "weight": 0.09
        },
        "6770 JT": {
            "id": "6770 JT",
            "name": "ALPS ALPINE CO LTD",
            "name_en": "Alps Alpine Co Ltd",
            "shares": 11300,
            "weight": 0.09
        },
        "8233 JT": {
            "id": "8233 JT",
            "name": "TAKASHIMAYA CO LTD",
            "name_en": "Takashimaya Co Ltd",
            "shares": 5600,
            "weight": 0.09
        },
        "8601 JT": {
            "id": "8601 JT",
            "name": "DAIWA SECURITIES GROUP INC",
            "name_en": "Daiwa Securities Group Inc",
            "shares": 11300,
            "weight": 0.09
        },
        "8804 JT": {
            "id": "8804 JT",
            "name": "TOKYO TATEMONO CO LTD",
            "name_en": "Tokyo Tatemono Co Ltd",
            "shares": 5600,
            "weight": 0.09
        },
        "1803 JT": {
            "id": "1803 JT",
            "name": "SHIMIZU CORP",
            "name_en": "Shimizu Corp",
            "shares": 11200,
            "weight": 0.08
        },
        "2531 JT": {
            "id": "2531 JT",
            "name": "TAKARA HOLDINGS INC",
            "name_en": "Takara Holdings Inc",
            "shares": 11200,
            "weight": 0.08
        },
        "4042 JT": {
            "id": "4042 JT",
            "name": "TOSOH CORP",
            "name_en": "Tosoh Corp",
            "shares": 5600,
            "weight": 0.08
        },
        "5301 JT": {
            "id": "5301 JT",
            "name": "TOKAI CARBON CO LTD",
            "name_en": "Tokai Carbon Co Ltd",
            "shares": 11300,
            "weight": 0.08
        },
        "5714 JT": {
            "id": "5714 JT",
            "name": "DOWA HOLDINGS CO LTD",
            "name_en": "Dowa Holdings Co Ltd",
            "shares": 2300,
            "weight": 0.08
        },
        "6701 JT": {
            "id": "6701 JT",
            "name": "NEC CORP",
            "name_en": "NEC Corp",
            "shares": 1100,
            "weight": 0.08
        },
        "7202 JT": {
            "id": "7202 JT",
            "name": "ISUZU MOTORS LTD",
            "name_en": "Isuzu Motors Ltd",
            "shares": 5600,
            "weight": 0.08
        },
        "7762 JT": {
            "id": "7762 JT",
            "name": "CITIZEN WATCH CO LTD",
            "name_en": "Citizen Watch Co Ltd",
            "shares": 11300,
            "weight": 0.08
        },
        "9005 JT": {
            "id": "9005 JT",
            "name": "TOKYU CORP",
            "name_en": "Tokyu Corp",
            "shares": 5600,
            "weight": 0.08
        },
        "9007 JT": {
            "id": "9007 JT",
            "name": "ODAKYU ELECTRIC RAILWAY CO",
            "name_en": "Odakyu Electric Railway Co Ltd",
            "shares": 5600,
            "weight": 0.08
        },
        "1332 JT": {
            "id": "1332 JT",
            "name": "NISSUI CORP",
            "name_en": "Nissui Corp",
            "shares": 11200,
            "weight": 0.07
        },
        "1605 JT": {
            "id": "1605 JT",
            "name": "INPEX CORP",
            "name_en": "Inpex Corp",
            "shares": 4400,
            "weight": 0.07
        },
        "4183 JT": {
            "id": "4183 JT",
            "name": "MITSUI CHEMICALS INC",
            "name_en": "Mitsui Chemicals Inc",
            "shares": 2300,
            "weight": 0.07
        },
        "4751 JT": {
            "id": "4751 JT",
            "name": "CYBERAGENT INC",
            "name_en": "CyberAgent Inc",
            "shares": 9000,
            "weight": 0.07
        },
        "4755 JT": {
            "id": "4755 JT",
            "name": "RAKUTEN GROUP INC",
            "name_en": "Rakuten Group Inc",
            "shares": 11300,
            "weight": 0.07
        },
        "6302 JT": {
            "id": "6302 JT",
            "name": "SUMITOMO HEAVY INDUSTRIES",
            "name_en": "Sumitomo Heavy Industries Ltd",
            "shares": 2300,
            "weight": 0.07
        },
        "8316 JT": {
            "id": "8316 JT",
            "name": "SUMITOMO MITSUI FINANCIAL GR",
            "name_en": "Sumitomo Mitsui Financial Group Inc",
            "shares": 1100,
            "weight": 0.07
        },
        "8604 JT": {
            "id": "8604 JT",
            "name": "NOMURA HOLDINGS INC",
            "name_en": "Nomura Holdings Inc",
            "shares": 11300,
            "weight": 0.07
        },
        "9008 JT": {
            "id": "9008 JT",
            "name": "KEIO CORP",
            "name_en": "Keio Corp",
            "shares": 2300,
            "weight": 0.07
        },
        "9020 JT": {
            "id": "9020 JT",
            "name": "EAST JAPAN RAILWAY CO",
            "name_en": "East Japan Railway Co",
            "shares": 1100,
            "weight": 0.07
        },
        "3086 JT": {
            "id": "3086 JT",
            "name": "J FRONT RETAILING CO LTD",
            "name_en": "J Front Retailing Co Ltd",
            "shares": 5500,
            "weight": 0.06
        },
        "3402 JT": {
            "id": "3402 JT",
            "name": "TORAY INDUSTRIES INC",
            "name_en": "Toray Industries Inc",
            "shares": 11300,
            "weight": 0.06
        },
        "5020 JT": {
            "id": "5020 JT",
            "name": "ENEOS HOLDINGS INC",
            "name_en": "ENEOS Holdings Inc",
            "shares": 11300,
            "weight": 0.06
        },
        "6471 JT": {
            "id": "6471 JT",
            "name": "NSK LTD",
            "name_en": "NSK Ltd",
            "shares": 11300,
            "weight": 0.06
        },
        "6753 JT": {
            "id": "6753 JT",
            "name": "SHARP CORP",
            "name_en": "Sharp Corp/Japan",
            "shares": 11300,
            "weight": 0.06
        },
        "7186 JT": {
            "id": "7186 JT",
            "name": "CONCORDIA FINANCIAL GROUP LT",
            "name_en": "Concordia Financial Group Ltd",
            "shares": 11300,
            "weight": 0.06
        },
        "8354 JT": {
            "id": "8354 JT",
            "name": "FUKUOKA FINANCIAL GROUP INC",
            "name_en": "Fukuoka Financial Group Inc",
            "shares": 2300,
            "weight": 0.06
        },
        "9001 JT": {
            "id": "9001 JT",
            "name": "TOBU RAILWAY CO LTD",
            "name_en": "Tobu Railway Co Ltd",
            "shares": 2300,
            "weight": 0.06
        },
        "9147 JT": {
            "id": "9147 JT",
            "name": "NIPPON EXPRESS HOLDINGS INC",
            "name_en": "NIPPON EXPRESS HOLDINGS INC",
            "shares": 1100,
            "weight": 0.06
        },
        "3861 JT": {
            "id": "3861 JT",
            "name": "OJI HOLDINGS CORP",
            "name_en": "Oji Holdings Corp",
            "shares": 11300,
            "weight": 0.05
        },
        "5631 JT": {
            "id": "5631 JT",
            "name": "JAPAN STEEL WORKS LTD",
            "name_en": "Japan Steel Works Ltd/The",
            "shares": 2300,
            "weight": 0.05
        },
        "6674 JT": {
            "id": "6674 JT",
            "name": "GS YUASA CORP",
            "name_en": "GS Yuasa Corp",
            "shares": 2300,
            "weight": 0.05
        },
        "7201 JT": {
            "id": "7201 JT",
            "name": "NISSAN MOTOR CO LTD",
            "name_en": "Nissan Motor Co Ltd",
            "shares": 11300,
            "weight": 0.05
        },
        "8309 JT": {
            "id": "8309 JT",
            "name": "SUMITOMO MITSUI TRUST HOLDIN",
            "name_en": "Sumitomo Mitsui Trust Holdings Inc",
            "shares": 2300,
            "weight": 0.05
        },
        "9021 JT": {
            "id": "9021 JT",
            "name": "WEST JAPAN RAILWAY CO",
            "name_en": "West Japan Railway Co",
            "shares": 1100,
            "weight": 0.05
        },
        "9531 JT": {
            "id": "9531 JT",
            "name": "TOKYO GAS CO LTD",
            "name_en": "Tokyo Gas Co Ltd",
            "shares": 2300,
            "weight": 0.05
        },
        "9532 JT": {
            "id": "9532 JT",
            "name": "OSAKA GAS CO LTD",
            "name_en": "Osaka Gas Co Ltd",
            "shares": 2300,
            "weight": 0.05
        },
        "4043 JT": {
            "id": "4043 JT",
            "name": "TOKUYAMA CORP",
            "name_en": "Tokuyama Corp",
            "shares": 2300,
            "weight": 0.04
        },
        "4061 JT": {
            "id": "4061 JT",
            "name": "DENKA CO LTD",
            "name_en": "Denka Co Ltd",
            "shares": 2300,
            "weight": 0.04
        },
        "4188 JT": {
            "id": "4188 JT",
            "name": "MITSUBISHI CHEMICAL GROUP CO",
            "name_en": "Mitsubishi Chemical Group Corp",
            "shares": 5600,
            "weight": 0.04
        },
        "4902 JT": {
            "id": "4902 JT",
            "name": "KONICA MINOLTA INC",
            "name_en": "Konica Minolta Inc",
            "shares": 11300,
            "weight": 0.04
        },
        "7012 JT": {
            "id": "7012 JT",
            "name": "KAWASAKI HEAVY INDUSTRIES",
            "name_en": "Kawasaki Heavy Industries Ltd",
            "shares": 1100,
            "weight": 0.04
        },
        "7205 JT": {
            "id": "7205 JT",
            "name": "HINO MOTORS LTD",
            "name_en": "Hino Motors Ltd",
            "shares": 11300,
            "weight": 0.04
        },
        "8795 JT": {
            "id": "8795 JT",
            "name": "T&D HOLDINGS INC",
            "name_en": "T&D Holdings Inc",
            "shares": 2300,
            "weight": 0.04
        },
        "9602 JT": {
            "id": "9602 JT",
            "name": "TOHO CO LTD",
            "name_en": "Toho Co Ltd/Tokyo",
            "shares": 1100,
            "weight": 0.04
        },
        "1808 JT": {
            "id": "1808 JT",
            "name": "HASEKO CORP",
            "name_en": "Haseko Corp",
            "shares": 2200,
            "weight": 0.03
        },
        "2432 JT": {
            "id": "2432 JT",
            "name": "DENA CO LTD",
            "name_en": "DeNA Co Ltd",
            "shares": 3300,
            "weight": 0.03
        },
        "2768 JT": {
            "id": "2768 JT",
            "name": "SOJITZ CORP",
            "name_en": "Sojitz Corp",
            "shares": 1120,
            "weight": 0.03
        },
        "4004 JT": {
            "id": "4004 JT",
            "name": "RESONAC HOLDINGS CORP",
            "name_en": "Resonac Holdings Corp",
            "shares": 1100,
            "weight": 0.03
        },
        "4005 JT": {
            "id": "4005 JT",
            "name": "SUMITOMO CHEMICAL CO LTD",
            "name_en": "Sumitomo Chemical Co Ltd",
            "shares": 11300,
            "weight": 0.03
        },
        "4506 JT": {
            "id": "4506 JT",
            "name": "SUMITOMO PHARMA CO LTD",
            "name_en": "Sumitomo Pharma Co Ltd",
            "shares": 11300,
            "weight": 0.03
        },
        "5232 JT": {
            "id": "5232 JT",
            "name": "SUMITOMO OSAKA CEMENT CO LTD",
            "name_en": "Sumitomo Osaka Cement Co Ltd",
            "shares": 1100,
            "weight": 0.03
        },
        "5233 JT": {
            "id": "5233 JT",
            "name": "TAIHEIYO CEMENT CORP",
            "name_en": "Taiheiyo Cement Corp",
            "shares": 1100,
            "weight": 0.03
        },
        "5401 JT": {
            "id": "5401 JT",
            "name": "NIPPON STEEL CORP",
            "name_en": "Nippon Steel Corp",
            "shares": 1100,
            "weight": 0.03
        },
        "5706 JT": {
            "id": "5706 JT",
            "name": "MITSUI MINING & SMELTING CO",
            "name_en": "Mitsui Mining & Smelting Co Ltd",
            "shares": 1100,
            "weight": 0.03
        },
        "7013 JT": {
            "id": "7013 JT",
            "name": "IHI CORP",
            "name_en": "IHI Corp",
            "shares": 1100,
            "weight": 0.03
        },
        "7261 JT": {
            "id": "7261 JT",
            "name": "MAZDA MOTOR CORP",
            "name_en": "Mazda Motor Corp",
            "shares": 2300,
            "weight": 0.03
        },
        "8750 JT": {
            "id": "8750 JT",
            "name": "DAI-ICHI LIFE HOLDINGS INC",
            "name_en": "Dai-ichi Life Holdings Inc",
            "shares": 1100,
            "weight": 0.03
        },
        "3401 JT": {
            "id": "3401 JT",
            "name": "TEIJIN LTD",
            "name_en": "Teijin Ltd",
            "shares": 2200,
            "weight": 0.02
        },
        "3436 JT": {
            "id": "3436 JT",
            "name": "SUMCO CORP",
            "name_en": "SUMCO Corp",
            "shares": 1100,
            "weight": 0.02
        },
        "4208 JT": {
            "id": "4208 JT",
            "name": "UBE CORP",
            "name_en": "UBE Corp",
            "shares": 1100,
            "weight": 0.02
        },
        "4631 JT": {
            "id": "4631 JT",
            "name": "DIC CORP",
            "name_en": "DIC Corp",
            "shares": 1100,
            "weight": 0.02
        },
        "5406 JT": {
            "id": "5406 JT",
            "name": "KOBE STEEL LTD",
            "name_en": "Kobe Steel Ltd",
            "shares": 1100,
            "weight": 0.02
        },
        "5411 JT": {
            "id": "5411 JT",
            "name": "JFE HOLDINGS INC",
            "name_en": "JFE Holdings Inc",
            "shares": 1100,
            "weight": 0.02
        },
        "5711 JT": {
            "id": "5711 JT",
            "name": "MITSUBISHI MATERIALS CORP",
            "name_en": "Mitsubishi Materials Corp",
            "shares": 1100,
            "weight": 0.02
        },
        "5801 JT": {
            "id": "5801 JT",
            "name": "FURUKAWA ELECTRIC CO LTD",
            "name_en": "Furukawa Electric Co Ltd",
            "shares": 1100,
            "weight": 0.02
        },
        "6472 JT": {
            "id": "6472 JT",
            "name": "NTN CORP",
            "name_en": "NTN Corp",
            "shares": 11300,
            "weight": 0.02
        },
        "7004 JT": {
            "id": "7004 JT",
            "name": "HITACHI ZOSEN CORP",
            "name_en": "Hitachi Zosen Corp",
            "shares": 2300,
            "weight": 0.02
        },
        "8304 JT": {
            "id": "8304 JT",
            "name": "AOZORA BANK LTD",
            "name_en": "Aozora Bank Ltd",
            "shares": 1100,
            "weight": 0.02
        },
        "8411 JT": {
            "id": "8411 JT",
            "name": "MIZUHO FINANCIAL GROUP INC",
            "name_en": "Mizuho Financial Group Inc",
            "shares": 1110,
            "weight": 0.02
        },
        "9202 JT": {
            "id": "9202 JT",
            "name": "ANA HOLDINGS INC",
            "name_en": "ANA Holdings Inc",
            "shares": 1100,
            "weight": 0.02
        },
        "9503 JT": {
            "id": "9503 JT",
            "name": "KANSAI ELECTRIC POWER CO INC",
            "name_en": "Kansai Electric Power Co Inc/The",
            "shares": 1100,
            "weight": 0.02
        },
        "3863 JT": {
            "id": "3863 JT",
            "name": "NIPPON PAPER INDUSTRIES CO L",
            "name_en": "Nippon Paper Industries Co Ltd",
            "shares": 1100,
            "weight": 0.01
        },
        "4689 JT": {
            "id": "4689 JT",
            "name": "LY CORP",
            "name_en": "LY Corp",
            "shares": 4500,
            "weight": 0.01
        },
        "5541 JT": {
            "id": "5541 JT",
            "name": "PACIFIC METALS CO LTD",
            "name_en": "Pacific Metals Co Ltd",
            "shares": 1100,
            "weight": 0.01
        },
        "8308 JT": {
            "id": "8308 JT",
            "name": "RESONA HOLDINGS INC",
            "name_en": "Resona Holdings Inc",
            "shares": 1100,
            "weight": 0.01
        },
        "9501 JT": {
            "id": "9501 JT",
            "name": "TOKYO ELECTRIC POWER COMPANY",
            "name_en": "Tokyo Electric Power Co Holdings Inc",
            "shares": 1100,
            "weight": 0.01
        },
        "9502 JT": {
            "id": "9502 JT",
            "name": "CHUBU ELECTRIC POWER CO INC",
            "name_en": "Chubu Electric Power Co Inc",
            "shares": 1100,
            "weight": 0.01
        },
        "7211 JT": {
            "id": "7211 JT",
            "name": "MITSUBISHI MOTORS CORP",
            "name_en": "Mitsubishi Motors Corp",
            "shares": 1100,
            "weight": 0
        }
    }
}