{
    "date": "2024-03-04",
    "amount": 1436117252,
    "shares": 139403000,
    "net": 10.3,
    "stocks": {
        "300750 CH": {
            "id": "300750 CH",
            "name": "寧德時代",
            "shares": 145320,
            "amount": 104275279,
            "weight": 7.2609,
            "price": 717.56
        },
        "000333 CH": {
            "id": "000333 CH",
            "name": "美的集團",
            "shares": 279900,
            "amount": 79161212,
            "weight": 5.5121,
            "price": 282.82
        },
        "000858 CH": {
            "id": "000858 CH",
            "name": "五 糧 液",
            "shares": 105400,
            "amount": 64754232,
            "weight": 4.5089,
            "price": 614.37
        },
        "000651 CH": {
            "id": "000651 CH",
            "name": "格力電器",
            "shares": 257300,
            "amount": 45137359,
            "weight": 3.143,
            "price": 175.43
        },
        "300059 CH": {
            "id": "300059 CH",
            "name": "東方財富",
            "shares": 727319,
            "amount": 44037650,
            "weight": 3.0664,
            "price": 60.55
        },
        "002594 CH": {
            "id": "002594 CH",
            "name": "比亞迪股份",
            "shares": 49200,
            "amount": 40768422,
            "weight": 2.8387,
            "price": 828.63
        },
        "300760 CH": {
            "id": "300760 CH",
            "name": "邁瑞醫療",
            "shares": 30600,
            "amount": 39012585,
            "weight": 2.7165,
            "price": 1274.92
        },
        "002475 CH": {
            "id": "002475 CH",
            "name": "立訊精密",
            "shares": 265333,
            "amount": 32537292,
            "weight": 2.2656,
            "price": 122.63
        },
        "000725 CH": {
            "id": "000725 CH",
            "name": "京東方",
            "shares": 1831400,
            "amount": 32472465,
            "weight": 2.2611,
            "price": 17.73
        },
        "000568 CH": {
            "id": "000568 CH",
            "name": "瀘州老窖",
            "shares": 43100,
            "amount": 32190914,
            "weight": 2.2415,
            "price": 746.89
        },
        "300124 CH": {
            "id": "300124 CH",
            "name": "匯川技術",
            "shares": 111230,
            "amount": 31579768,
            "weight": 2.1989,
            "price": 283.91
        },
        "300308 CH": {
            "id": "300308 CH",
            "name": "中際旭創",
            "shares": 36300,
            "amount": 26326995,
            "weight": 1.8332,
            "price": 725.26
        },
        "300498 CH": {
            "id": "300498 CH",
            "name": "溫氏股份",
            "shares": 313260,
            "amount": 25934238,
            "weight": 1.8058,
            "price": 82.79
        },
        "000063 CH": {
            "id": "000063 CH",
            "name": "中興通訊",
            "shares": 184300,
            "amount": 24423887,
            "weight": 1.7006,
            "price": 132.52
        },
        "002230 CH": {
            "id": "002230 CH",
            "name": "科大訊飛",
            "shares": 105100,
            "amount": 24078557,
            "weight": 1.6766,
            "price": 229.1
        },
        "002714 CH": {
            "id": "002714 CH",
            "name": "牧原股份",
            "shares": 143554,
            "amount": 23700027,
            "weight": 1.6502,
            "price": 165.09
        },
        "300274 CH": {
            "id": "300274 CH",
            "name": "陽光電源",
            "shares": 58100,
            "amount": 22760360,
            "weight": 1.5848,
            "price": 391.74
        },
        "000001 CH": {
            "id": "000001 CH",
            "name": "平安銀行",
            "shares": 490100,
            "amount": 22164709,
            "weight": 1.5433,
            "price": 45.22
        },
        "002352 CH": {
            "id": "002352 CH",
            "name": "順豐控股",
            "shares": 132100,
            "amount": 21913131,
            "weight": 1.5258,
            "price": 165.88
        },
        "000100 CH": {
            "id": "000100 CH",
            "name": "TCL 集團",
            "shares": 1051550,
            "amount": 21775498,
            "weight": 1.5162,
            "price": 20.71
        },
        "000338 CH": {
            "id": "000338 CH",
            "name": "濰柴動力",
            "shares": 298700,
            "amount": 21211095,
            "weight": 1.4769,
            "price": 71.01
        },
        "002371 CH": {
            "id": "002371 CH",
            "name": "北方華創",
            "shares": 16000,
            "amount": 20465983,
            "weight": 1.425,
            "price": 1279.12
        },
        "002142 CH": {
            "id": "002142 CH",
            "name": "寧波銀行",
            "shares": 200444,
            "amount": 18893574,
            "weight": 1.3156,
            "price": 94.26
        },
        "000792 CH": {
            "id": "000792 CH",
            "name": "鹽湖股份",
            "shares": 224000,
            "amount": 16318430,
            "weight": 1.1362,
            "price": 72.85
        },
        "002027 CH": {
            "id": "002027 CH",
            "name": "分眾傳媒",
            "shares": 584640,
            "amount": 16304406,
            "weight": 1.1353,
            "price": 27.89
        },
        "000625 CH": {
            "id": "000625 CH",
            "name": "長安汽車",
            "shares": 245476,
            "amount": 15787300,
            "weight": 1.0993,
            "price": 64.31
        },
        "300015 CH": {
            "id": "300015 CH",
            "name": "愛爾眼科",
            "shares": 248403,
            "amount": 15747166,
            "weight": 1.0965,
            "price": 63.39
        },
        "300122 CH": {
            "id": "300122 CH",
            "name": "智飛生物",
            "shares": 65650,
            "amount": 15644082,
            "weight": 1.0893,
            "price": 238.3
        },
        "002304 CH": {
            "id": "002304 CH",
            "name": "洋河股份",
            "shares": 34600,
            "amount": 15060066,
            "weight": 1.0486,
            "price": 435.26
        },
        "000002 CH": {
            "id": "000002 CH",
            "name": "萬科企業",
            "shares": 355100,
            "amount": 14660183,
            "weight": 1.0208,
            "price": 41.28
        },
        "002466 CH": {
            "id": "002466 CH",
            "name": "天齊鋰業",
            "shares": 59400,
            "amount": 13772457,
            "weight": 0.959,
            "price": 231.86
        },
        "002050 CH": {
            "id": "002050 CH",
            "name": "三花智控",
            "shares": 119500,
            "amount": 13602486,
            "weight": 0.9471,
            "price": 113.83
        },
        "300014 CH": {
            "id": "300014 CH",
            "name": "億緯鋰能",
            "shares": 73100,
            "amount": 12458874,
            "weight": 0.8675,
            "price": 170.44
        },
        "002049 CH": {
            "id": "002049 CH",
            "name": "紫光國微",
            "shares": 37740,
            "amount": 12304395,
            "weight": 0.8567,
            "price": 326.03
        },
        "002460 CH": {
            "id": "002460 CH",
            "name": "贛鋒鋰業",
            "shares": 64640,
            "amount": 11325449,
            "weight": 0.7886,
            "price": 175.21
        },
        "000938 CH": {
            "id": "000938 CH",
            "name": "紫光股份",
            "shares": 100472,
            "amount": 11216626,
            "weight": 0.781,
            "price": 111.64
        },
        "000425 CH": {
            "id": "000425 CH",
            "name": "徐工機械",
            "shares": 402000,
            "amount": 10929359,
            "weight": 0.761,
            "price": 27.19
        },
        "002241 CH": {
            "id": "002241 CH",
            "name": "歌爾股份",
            "shares": 141300,
            "amount": 10664892,
            "weight": 0.7426,
            "price": 75.48
        },
        "000166 CH": {
            "id": "000166 CH",
            "name": "申萬宏源",
            "shares": 523000,
            "amount": 10349447,
            "weight": 0.7206,
            "price": 19.79
        },
        "000776 CH": {
            "id": "000776 CH",
            "name": "廣發証券",
            "shares": 164000,
            "amount": 10130896,
            "weight": 0.7054,
            "price": 61.77
        },
        "000661 CH": {
            "id": "000661 CH",
            "name": "長春高新",
            "shares": 17500,
            "amount": 10000585,
            "weight": 0.6963,
            "price": 571.46
        },
        "000538 CH": {
            "id": "000538 CH",
            "name": "雲南白藥",
            "shares": 45020,
            "amount": 9984991,
            "weight": 0.6952,
            "price": 221.79
        },
        "002129 CH": {
            "id": "002129 CH",
            "name": "中環股份",
            "shares": 169975,
            "amount": 9964205,
            "weight": 0.6938,
            "price": 58.62
        },
        "300782 CH": {
            "id": "300782 CH",
            "name": "卓勝微",
            "shares": 19432,
            "amount": 9555460,
            "weight": 0.6653,
            "price": 491.74
        },
        "000157 CH": {
            "id": "000157 CH",
            "name": "中聯重科",
            "shares": 259100,
            "amount": 9074744,
            "weight": 0.6318,
            "price": 35.02
        },
        "002459 CH": {
            "id": "002459 CH",
            "name": "晶澳科技",
            "shares": 104212,
            "amount": 8581902,
            "weight": 0.5975,
            "price": 82.35
        },
        "002236 CH": {
            "id": "002236 CH",
            "name": "大華股份",
            "shares": 101200,
            "amount": 8449056,
            "weight": 0.5883,
            "price": 83.49
        },
        "002311 CH": {
            "id": "002311 CH",
            "name": "海大集團",
            "shares": 45200,
            "amount": 8435887,
            "weight": 0.5874,
            "price": 186.63
        },
        "000596 CH": {
            "id": "000596 CH",
            "name": "古井貢酒",
            "shares": 8300,
            "amount": 8149049,
            "weight": 0.5674,
            "price": 981.81
        },
        "002271 CH": {
            "id": "002271 CH",
            "name": "東方雨虹",
            "shares": 111298,
            "amount": 8147055,
            "weight": 0.5672,
            "price": 73.2
        },
        "300896 CH": {
            "id": "300896 CH",
            "name": "愛美客",
            "shares": 5700,
            "amount": 8049878,
            "weight": 0.5605,
            "price": 1412.26
        },
        "300408 CH": {
            "id": "300408 CH",
            "name": "三環集團",
            "shares": 71200,
            "amount": 8020414,
            "weight": 0.5584,
            "price": 112.65
        },
        "000895 CH": {
            "id": "000895 CH",
            "name": "雙匯發展",
            "shares": 61800,
            "amount": 7997789,
            "weight": 0.5569,
            "price": 129.41
        },
        "002493 CH": {
            "id": "002493 CH",
            "name": "榮盛石化",
            "shares": 175600,
            "amount": 7956863,
            "weight": 0.554,
            "price": 45.31
        },
        "300142 CH": {
            "id": "300142 CH",
            "name": "沃森生物",
            "shares": 94200,
            "amount": 7691424,
            "weight": 0.5355,
            "price": 81.65
        },
        "002555 CH": {
            "id": "002555 CH",
            "name": "三七互娛",
            "shares": 85000,
            "amount": 7330982,
            "weight": 0.5104,
            "price": 86.25
        },
        "000983 CH": {
            "id": "000983 CH",
            "name": "山西焦煤",
            "shares": 140700,
            "amount": 7317918,
            "weight": 0.5095,
            "price": 52.01
        },
        "002601 CH": {
            "id": "002601 CH",
            "name": "龍蟒佰利",
            "shares": 88500,
            "amount": 7260891,
            "weight": 0.5055,
            "price": 82.04
        },
        "300033 CH": {
            "id": "300033 CH",
            "name": "同花順",
            "shares": 11500,
            "amount": 7222801,
            "weight": 0.5029,
            "price": 628.07
        },
        "002001 CH": {
            "id": "002001 CH",
            "name": "新 和 成",
            "shares": 89944,
            "amount": 7158847,
            "weight": 0.4984,
            "price": 79.59
        },
        "003816 CH": {
            "id": "003816 CH",
            "name": "中廣核電力",
            "shares": 404200,
            "amount": 7025283,
            "weight": 0.4891,
            "price": 17.38
        },
        "002920 CH": {
            "id": "002920 CH",
            "name": "德賽西威",
            "shares": 14800,
            "amount": 6646629,
            "weight": 0.4628,
            "price": 449.1
        },
        "000301 CH": {
            "id": "000301 CH",
            "name": "東方盛虹",
            "shares": 143800,
            "amount": 6459267,
            "weight": 0.4497,
            "price": 44.92
        },
        "000963 CH": {
            "id": "000963 CH",
            "name": "華東醫藥",
            "shares": 43900,
            "amount": 6438524,
            "weight": 0.4483,
            "price": 146.66
        },
        "000786 CH": {
            "id": "000786 CH",
            "name": "北新建材",
            "shares": 52900,
            "amount": 6385125,
            "weight": 0.4446,
            "price": 120.7
        },
        "001979 CH": {
            "id": "001979 CH",
            "name": "招商蛇口",
            "shares": 163463,
            "amount": 6383536,
            "weight": 0.4444,
            "price": 39.05
        },
        "300347 CH": {
            "id": "300347 CH",
            "name": "泰格醫藥",
            "shares": 30600,
            "amount": 6264306,
            "weight": 0.4361,
            "price": 204.72
        },
        "002709 CH": {
            "id": "002709 CH",
            "name": "天賜材料",
            "shares": 69300,
            "amount": 6171081,
            "weight": 0.4297,
            "price": 89.05
        },
        "300433 CH": {
            "id": "300433 CH",
            "name": "藍思科技",
            "shares": 112195,
            "amount": 6144801,
            "weight": 0.4278,
            "price": 54.77
        },
        "002736 CH": {
            "id": "002736 CH",
            "name": "國信證券",
            "shares": 158800,
            "amount": 5978965,
            "weight": 0.4163,
            "price": 37.65
        },
        "002821 CH": {
            "id": "002821 CH",
            "name": "凱萊英",
            "shares": 12540,
            "amount": 5952288,
            "weight": 0.4144,
            "price": 474.66
        },
        "002812 CH": {
            "id": "002812 CH",
            "name": "恩捷股份",
            "shares": 29500,
            "amount": 5802771,
            "weight": 0.404,
            "price": 196.7
        },
        "300759 CH": {
            "id": "300759 CH",
            "name": "康龍化成",
            "shares": 53200,
            "amount": 5792479,
            "weight": 0.4033,
            "price": 108.88
        },
        "300316 CH": {
            "id": "300316 CH",
            "name": "晶盛機電",
            "shares": 35400,
            "amount": 5738971,
            "weight": 0.3996,
            "price": 162.12
        },
        "300450 CH": {
            "id": "300450 CH",
            "name": "先導智能",
            "shares": 57400,
            "amount": 5694412,
            "weight": 0.3965,
            "price": 99.21
        },
        "002180 CH": {
            "id": "002180 CH",
            "name": "納思達",
            "shares": 52200,
            "amount": 5665315,
            "weight": 0.3944,
            "price": 108.53
        },
        "300661 CH": {
            "id": "300661 CH",
            "name": "聖邦股份",
            "shares": 17360,
            "amount": 5465325,
            "weight": 0.3805,
            "price": 314.82
        },
        "000876 CH": {
            "id": "000876 CH",
            "name": "新 希 望",
            "shares": 123300,
            "amount": 4809697,
            "weight": 0.3349,
            "price": 39.01
        },
        "002410 CH": {
            "id": "002410 CH",
            "name": "廣聯達",
            "shares": 79420,
            "amount": 4756560,
            "weight": 0.3312,
            "price": 59.89
        },
        "300999 CH": {
            "id": "300999 CH",
            "name": "金龍魚",
            "shares": 32600,
            "amount": 4517190,
            "weight": 0.3145,
            "price": 138.56
        },
        "002603 CH": {
            "id": "002603 CH",
            "name": "以嶺藥業",
            "shares": 44900,
            "amount": 4291184,
            "weight": 0.2988,
            "price": 95.57
        },
        "300751 CH": {
            "id": "300751 CH",
            "name": "邁為股份",
            "shares": 8160,
            "amount": 4279091,
            "weight": 0.2979,
            "price": 524.4
        },
        "301269 CH": {
            "id": "301269 CH",
            "name": "華大九天",
            "shares": 10100,
            "amount": 4073355,
            "weight": 0.2836,
            "price": 403.3
        },
        "300413 CH": {
            "id": "300413 CH",
            "name": "芒果超媒",
            "shares": 35810,
            "amount": 3950771,
            "weight": 0.2751,
            "price": 110.33
        },
        "300454 CH": {
            "id": "300454 CH",
            "name": "深信服",
            "shares": 13800,
            "amount": 3878140,
            "weight": 0.27,
            "price": 281.02
        },
        "000617 CH": {
            "id": "000617 CH",
            "name": "中油資本",
            "shares": 144820,
            "amount": 3842184,
            "weight": 0.2675,
            "price": 26.53
        },
        "002841 CH": {
            "id": "002841 CH",
            "name": "視源股份",
            "shares": 20600,
            "amount": 3607482,
            "weight": 0.2511,
            "price": 175.12
        },
        "300919 CH": {
            "id": "300919 CH",
            "name": "中偉股份",
            "shares": 17300,
            "amount": 3605205,
            "weight": 0.251,
            "price": 208.39
        },
        "002938 CH": {
            "id": "002938 CH",
            "name": "鵬鼎控股",
            "shares": 35700,
            "amount": 3551023,
            "weight": 0.2472,
            "price": 99.47
        },
        "002916 CH": {
            "id": "002916 CH",
            "name": "深南電路",
            "shares": 10900,
            "amount": 3527488,
            "weight": 0.2456,
            "price": 323.62
        },
        "300628 CH": {
            "id": "300628 CH",
            "name": "億聯網路",
            "shares": 26380,
            "amount": 3371211,
            "weight": 0.2347,
            "price": 127.79
        },
        "000708 CH": {
            "id": "000708 CH",
            "name": "中信特鋼",
            "shares": 48900,
            "amount": 3228399,
            "weight": 0.2248,
            "price": 66.02
        },
        "001965 CH": {
            "id": "001965 CH",
            "name": "招商公路",
            "shares": 53100,
            "amount": 2489780,
            "weight": 0.1733,
            "price": 46.89
        },
        "000877 CH": {
            "id": "000877 CH",
            "name": "天山股份",
            "shares": 80600,
            "amount": 2371272,
            "weight": 0.1651,
            "price": 29.42
        },
        "300957 CH": {
            "id": "300957 CH",
            "name": "貝泰妮",
            "shares": 7700,
            "amount": 2213107,
            "weight": 0.1541,
            "price": 287.42
        },
        "300979 CH": {
            "id": "300979 CH",
            "name": "華利集團",
            "shares": 8800,
            "amount": 2182527,
            "weight": 0.1519,
            "price": 248.01
        },
        "001289 CH": {
            "id": "001289 CH",
            "name": "龍源電力",
            "shares": 8000,
            "amount": 661255,
            "weight": 0.046,
            "price": 82.66
        }
    },
    "deposit": 15476850,
    "cash": 4803821
}