{
    "date": "2024-03-11",
    "amount": 24853961688,
    "shares": 674280000,
    "net": 36.86,
    "stocks": {
        "2330": {
            "id": "2330",
            "name": "台積電",
            "shares": 14254100,
            "amount": 10918640600,
            "weight": 43.9311,
            "price": 766
        },
        "2454": {
            "id": "2454",
            "name": "聯發科",
            "shares": 878900,
            "amount": 1076652500,
            "weight": 4.3319,
            "price": 1225
        },
        "2317": {
            "id": "2317",
            "name": "鴻海",
            "shares": 7621000,
            "amount": 834499500,
            "weight": 3.3576,
            "price": 109.5
        },
        "2382": {
            "id": "2382",
            "name": "廣達",
            "shares": 2123000,
            "amount": 529688500,
            "weight": 2.1312,
            "price": 249.5
        },
        "2412": {
            "id": "2412",
            "name": "中華電",
            "shares": 4264200,
            "amount": 518100300,
            "weight": 2.0845,
            "price": 121.5
        },
        "2881": {
            "id": "2881",
            "name": "富邦金",
            "shares": 7153978,
            "amount": 495055278,
            "weight": 1.9918,
            "price": 69.2
        },
        "2308": {
            "id": "2308",
            "name": "台達電",
            "shares": 1427300,
            "amount": 439608400,
            "weight": 1.7687,
            "price": 308
        },
        "6505": {
            "id": "6505",
            "name": "台塑化",
            "shares": 5237000,
            "amount": 372350700,
            "weight": 1.4981,
            "price": 71.1
        },
        "2882": {
            "id": "2882",
            "name": "國泰金",
            "shares": 8063113,
            "amount": 371306354,
            "weight": 1.4939,
            "price": 46.05
        },
        "3711": {
            "id": "3711",
            "name": "日月光投控",
            "shares": 2410900,
            "amount": 371278600,
            "weight": 1.4938,
            "price": 154
        },
        "2303": {
            "id": "2303",
            "name": "聯電",
            "shares": 6888500,
            "amount": 355446600,
            "weight": 1.4301,
            "price": 51.6
        },
        "2891": {
            "id": "2891",
            "name": "中信金",
            "shares": 10786300,
            "amount": 326824890,
            "weight": 1.3149,
            "price": 30.3
        },
        "2886": {
            "id": "2886",
            "name": "兆豐金",
            "shares": 7916174,
            "amount": 315063725,
            "weight": 1.2676,
            "price": 39.8
        },
        "1303": {
            "id": "1303",
            "name": "南亞",
            "shares": 4359500,
            "amount": 244567950,
            "weight": 0.984,
            "price": 56.1
        },
        "1301": {
            "id": "1301",
            "name": "台塑",
            "shares": 3499900,
            "amount": 241143110,
            "weight": 0.9702,
            "price": 68.9
        },
        "1216": {
            "id": "1216",
            "name": "統一",
            "shares": 3123200,
            "amount": 239237120,
            "weight": 0.9625,
            "price": 76.6
        },
        "6669": {
            "id": "6669",
            "name": "緯穎",
            "shares": 97000,
            "amount": 235710000,
            "weight": 0.9483,
            "price": 2430
        },
        "2884": {
            "id": "2884",
            "name": "玉山金",
            "shares": 8610923,
            "amount": 219578537,
            "weight": 0.8834,
            "price": 25.5
        },
        "2603": {
            "id": "2603",
            "name": "長榮",
            "shares": 1163702,
            "amount": 209466360,
            "weight": 0.8427,
            "price": 180
        },
        "5880": {
            "id": "5880",
            "name": "合庫金",
            "shares": 8087167,
            "amount": 209053267,
            "weight": 0.8411,
            "price": 25.85
        },
        "2002": {
            "id": "2002",
            "name": "中鋼",
            "shares": 8649000,
            "amount": 208008450,
            "weight": 0.8369,
            "price": 24.05
        },
        "2892": {
            "id": "2892",
            "name": "第一金",
            "shares": 7487092,
            "amount": 202525839,
            "weight": 0.8148,
            "price": 27.05
        },
        "3045": {
            "id": "3045",
            "name": "台灣大",
            "shares": 2046700,
            "amount": 202213960,
            "weight": 0.8136,
            "price": 98.8
        },
        "2885": {
            "id": "2885",
            "name": "元大金",
            "shares": 6974693,
            "amount": 199127485,
            "weight": 0.8011,
            "price": 28.55
        },
        "3034": {
            "id": "3034",
            "name": "聯詠",
            "shares": 334000,
            "amount": 194388000,
            "weight": 0.7821,
            "price": 582
        },
        "3231": {
            "id": "3231",
            "name": "緯創",
            "shares": 1594548,
            "amount": 192940308,
            "weight": 0.7762,
            "price": 121
        },
        "2395": {
            "id": "2395",
            "name": "研華",
            "shares": 470611,
            "amount": 191303372,
            "weight": 0.7697,
            "price": 406.5
        },
        "2357": {
            "id": "2357",
            "name": "華碩",
            "shares": 408400,
            "amount": 181329600,
            "weight": 0.7295,
            "price": 444
        },
        "1326": {
            "id": "1326",
            "name": "台化",
            "shares": 3221900,
            "amount": 178171070,
            "weight": 0.7168,
            "price": 55.3
        },
        "2379": {
            "id": "2379",
            "name": "瑞昱",
            "shares": 281000,
            "amount": 169724000,
            "weight": 0.6828,
            "price": 604
        },
        "2880": {
            "id": "2880",
            "name": "華南金",
            "shares": 7498334,
            "amount": 164963348,
            "weight": 0.6637,
            "price": 22
        },
        "5871": {
            "id": "5871",
            "name": "中租-KY",
            "shares": 888441,
            "amount": 155032955,
            "weight": 0.6237,
            "price": 174.5
        },
        "2912": {
            "id": "2912",
            "name": "統一超",
            "shares": 572000,
            "amount": 153296000,
            "weight": 0.6167,
            "price": 268
        },
        "4904": {
            "id": "4904",
            "name": "遠傳",
            "shares": 1930300,
            "amount": 151528550,
            "weight": 0.6096,
            "price": 78.5
        },
        "3037": {
            "id": "3037",
            "name": "欣興",
            "shares": 839000,
            "amount": 148503000,
            "weight": 0.5975,
            "price": 177
        },
        "2301": {
            "id": "2301",
            "name": "光寶科",
            "shares": 1293000,
            "amount": 146755500,
            "weight": 0.5904,
            "price": 113.5
        },
        "2890": {
            "id": "2890",
            "name": "永豐金",
            "shares": 6803075,
            "amount": 137762269,
            "weight": 0.5542,
            "price": 20.25
        },
        "1101": {
            "id": "1101",
            "name": "台泥",
            "shares": 4151000,
            "amount": 132001800,
            "weight": 0.5311,
            "price": 31.8
        },
        "4938": {
            "id": "4938",
            "name": "和碩",
            "shares": 1464000,
            "amount": 124586400,
            "weight": 0.5012,
            "price": 85.1
        },
        "2887": {
            "id": "2887",
            "name": "台新金",
            "shares": 6858705,
            "amount": 122084949,
            "weight": 0.4912,
            "price": 17.8
        },
        "5876": {
            "id": "5876",
            "name": "上海商銀",
            "shares": 2672000,
            "amount": 119171200,
            "weight": 0.4794,
            "price": 44.6
        },
        "2408": {
            "id": "2408",
            "name": "南亞科",
            "shares": 1703100,
            "amount": 112063980,
            "weight": 0.4508,
            "price": 65.8
        },
        "3443": {
            "id": "3443",
            "name": "創意",
            "shares": 74000,
            "amount": 109150000,
            "weight": 0.4391,
            "price": 1475
        },
        "2801": {
            "id": "2801",
            "name": "彰銀",
            "shares": 5968100,
            "amount": 106828990,
            "weight": 0.4298,
            "price": 17.9
        },
        "1402": {
            "id": "1402",
            "name": "遠東新",
            "shares": 2943200,
            "amount": 95654000,
            "weight": 0.3848,
            "price": 32.5
        },
        "2618": {
            "id": "2618",
            "name": "長榮航",
            "shares": 2968000,
            "amount": 94679200,
            "weight": 0.3809,
            "price": 31.9
        },
        "2609": {
            "id": "2609",
            "name": "陽明",
            "shares": 1920000,
            "amount": 93312000,
            "weight": 0.3754,
            "price": 48.6
        },
        "2385": {
            "id": "2385",
            "name": "群光",
            "shares": 418000,
            "amount": 91751000,
            "weight": 0.3691,
            "price": 219.5
        },
        "3036": {
            "id": "3036",
            "name": "文曄",
            "shares": 562502,
            "amount": 89156567,
            "weight": 0.3587,
            "price": 158.5
        },
        "3702": {
            "id": "3702",
            "name": "大聯大",
            "shares": 923000,
            "amount": 86300500,
            "weight": 0.3472,
            "price": 93.5
        },
        "1476": {
            "id": "1476",
            "name": "儒鴻",
            "shares": 150500,
            "amount": 85032500,
            "weight": 0.3421,
            "price": 565
        },
        "6409": {
            "id": "6409",
            "name": "旭隼",
            "shares": 48782,
            "amount": 80978120,
            "weight": 0.3258,
            "price": 1660
        },
        "1605": {
            "id": "1605",
            "name": "華新",
            "shares": 2216000,
            "amount": 78778800,
            "weight": 0.3169,
            "price": 35.55
        },
        "1102": {
            "id": "1102",
            "name": "亞泥",
            "shares": 1948100,
            "amount": 78703240,
            "weight": 0.3166,
            "price": 40.4
        },
        "2615": {
            "id": "2615",
            "name": "萬海",
            "shares": 1542050,
            "amount": 76023065,
            "weight": 0.3058,
            "price": 49.3
        },
        "8046": {
            "id": "8046",
            "name": "南電",
            "shares": 355000,
            "amount": 73662500,
            "weight": 0.2963,
            "price": 207.5
        },
        "6239": {
            "id": "6239",
            "name": "力成",
            "shares": 416000,
            "amount": 70720000,
            "weight": 0.2845,
            "price": 170
        },
        "2834": {
            "id": "2834",
            "name": "臺企銀",
            "shares": 4521096,
            "amount": 65781947,
            "weight": 0.2646,
            "price": 14.55
        },
        "2371": {
            "id": "2371",
            "name": "大同",
            "shares": 1285000,
            "amount": 65663500,
            "weight": 0.2641,
            "price": 51.1
        },
        "2344": {
            "id": "2344",
            "name": "華邦電",
            "shares": 2298703,
            "amount": 63099397,
            "weight": 0.2538,
            "price": 27.45
        },
        "6770": {
            "id": "6770",
            "name": "力積電",
            "shares": 2238000,
            "amount": 60314100,
            "weight": 0.2426,
            "price": 26.95
        },
        "1504": {
            "id": "1504",
            "name": "東元",
            "shares": 1176000,
            "amount": 59152800,
            "weight": 0.238,
            "price": 50.3
        },
        "8454": {
            "id": "8454",
            "name": "富邦媒",
            "shares": 131444,
            "amount": 52906210,
            "weight": 0.2128,
            "price": 402.5
        },
        "4958": {
            "id": "4958",
            "name": "臻鼎-KY",
            "shares": 520400,
            "amount": 52560400,
            "weight": 0.2114,
            "price": 101
        },
        "9904": {
            "id": "9904",
            "name": "寶成",
            "shares": 1620000,
            "amount": 50463000,
            "weight": 0.203,
            "price": 31.15
        },
        "3035": {
            "id": "3035",
            "name": "智原",
            "shares": 136000,
            "amount": 49368000,
            "weight": 0.1986,
            "price": 363
        },
        "2812": {
            "id": "2812",
            "name": "台中銀",
            "shares": 2874000,
            "amount": 49289100,
            "weight": 0.1983,
            "price": 17.15
        },
        "1477": {
            "id": "1477",
            "name": "聚陽",
            "shares": 134000,
            "amount": 48977000,
            "weight": 0.197,
            "price": 365.5
        },
        "2049": {
            "id": "2049",
            "name": "上銀",
            "shares": 194456,
            "amount": 46863896,
            "weight": 0.1885,
            "price": 241
        },
        "2352": {
            "id": "2352",
            "name": "佳世達",
            "shares": 1080900,
            "amount": 46748925,
            "weight": 0.188,
            "price": 43.25
        },
        "9941": {
            "id": "9941",
            "name": "裕融",
            "shares": 300924,
            "amount": 43784442,
            "weight": 0.1761,
            "price": 145.5
        },
        "2633": {
            "id": "2633",
            "name": "台灣高鐵",
            "shares": 1446000,
            "amount": 43235400,
            "weight": 0.1739,
            "price": 29.9
        },
        "6285": {
            "id": "6285",
            "name": "啟碁",
            "shares": 264241,
            "amount": 37786463,
            "weight": 0.152,
            "price": 143
        },
        "3023": {
            "id": "3023",
            "name": "信邦",
            "shares": 133000,
            "amount": 35710500,
            "weight": 0.1436,
            "price": 268.5
        },
        "6592": {
            "id": "6592",
            "name": "和潤企業",
            "shares": 311100,
            "amount": 35620950,
            "weight": 0.1433,
            "price": 114.5
        },
        "3532": {
            "id": "3532",
            "name": "台勝科",
            "shares": 213000,
            "amount": 34399500,
            "weight": 0.1384,
            "price": 161.5
        },
        "2006": {
            "id": "2006",
            "name": "東和鋼鐵",
            "shares": 401570,
            "amount": 31201989,
            "weight": 0.1255,
            "price": 77.7
        },
        "3706": {
            "id": "3706",
            "name": "神達",
            "shares": 664000,
            "amount": 29016800,
            "weight": 0.1167,
            "price": 43.7
        },
        "2337": {
            "id": "2337",
            "name": "旺宏",
            "shares": 1019000,
            "amount": 27971550,
            "weight": 0.1125,
            "price": 27.45
        },
        "2606": {
            "id": "2606",
            "name": "裕民",
            "shares": 465000,
            "amount": 26226000,
            "weight": 0.1055,
            "price": 56.4
        },
        "2637": {
            "id": "2637",
            "name": "慧洋-KY",
            "shares": 410000,
            "amount": 25256000,
            "weight": 0.1016,
            "price": 61.6
        },
        "2634": {
            "id": "2634",
            "name": "漢翔",
            "shares": 518000,
            "amount": 24630900,
            "weight": 0.0991,
            "price": 47.55
        },
        "2015": {
            "id": "2015",
            "name": "豐興",
            "shares": 319000,
            "amount": 22840400,
            "weight": 0.0918,
            "price": 71.6
        },
        "5434": {
            "id": "5434",
            "name": "崇越",
            "shares": 103773,
            "amount": 21896103,
            "weight": 0.088,
            "price": 211
        },
        "3665": {
            "id": "3665",
            "name": "貿聯-KY",
            "shares": 89147,
            "amount": 21439854,
            "weight": 0.0862,
            "price": 240.5
        },
        "6414": {
            "id": "6414",
            "name": "樺漢",
            "shares": 69000,
            "amount": 20010000,
            "weight": 0.0805,
            "price": 290
        },
        "9933": {
            "id": "9933",
            "name": "中鼎",
            "shares": 441000,
            "amount": 19955250,
            "weight": 0.0802,
            "price": 45.25
        },
        "4766": {
            "id": "4766",
            "name": "南寶",
            "shares": 67000,
            "amount": 19631000,
            "weight": 0.0789,
            "price": 293
        },
        "2897": {
            "id": "2897",
            "name": "王道銀行",
            "shares": 1504000,
            "amount": 15115200,
            "weight": 0.0608,
            "price": 10.05
        },
        "1723": {
            "id": "1723",
            "name": "中碳",
            "shares": 130000,
            "amount": 14495000,
            "weight": 0.0583,
            "price": 111.5
        },
        "6579": {
            "id": "6579",
            "name": "研揚",
            "shares": 89000,
            "amount": 13483500,
            "weight": 0.0542,
            "price": 151.5
        },
        "9802": {
            "id": "9802",
            "name": "鈺齊-KY",
            "shares": 106000,
            "amount": 13144000,
            "weight": 0.0528,
            "price": 124
        },
        "3703": {
            "id": "3703",
            "name": "欣陸",
            "shares": 453000,
            "amount": 12910500,
            "weight": 0.0519,
            "price": 28.5
        },
        "2530": {
            "id": "2530",
            "name": "華建",
            "shares": 286000,
            "amount": 11382800,
            "weight": 0.0457,
            "price": 39.8
        },
        "2103": {
            "id": "2103",
            "name": "台橡",
            "shares": 454000,
            "amount": 10419300,
            "weight": 0.0419,
            "price": 22.95
        },
        "1712": {
            "id": "1712",
            "name": "興農",
            "shares": 232000,
            "amount": 9720800,
            "weight": 0.0391,
            "price": 41.9
        },
        "8163": {
            "id": "8163",
            "name": "達方",
            "shares": 154000,
            "amount": 9178400,
            "weight": 0.0369,
            "price": 59.6
        },
        "3454": {
            "id": "3454",
            "name": "晶睿",
            "shares": 48000,
            "amount": 6984000,
            "weight": 0.0281,
            "price": 145.5
        },
        "5288": {
            "id": "5288",
            "name": "豐祥-KY",
            "shares": 37000,
            "amount": 6641500,
            "weight": 0.0267,
            "price": 179.5
        },
        "2546": {
            "id": "2546",
            "name": "根基",
            "shares": 67100,
            "amount": 5911510,
            "weight": 0.0237,
            "price": 88.1
        }
    },
    "deposit": 28963547,
    "cash": 20021091
}