{
    "date": "2024-03-18",
    "amount": 1180959287,
    "shares": 34186000,
    "net": 34.5451,
    "stocks": {
        "US91282CJJ18": {
            "id": "US91282CJJ18",
            "name": "T 4 1/2 11/15/33",
            "shares": 3590000,
            "amount": 115026836,
            "weight": 9.7401,
            "price": 32.04
        },
        "US91282CHT18": {
            "id": "US91282CHT18",
            "name": "T 3 7/8 08/15/33",
            "shares": 3527000,
            "amount": 107616971,
            "weight": 9.1126,
            "price": 30.51
        },
        "US91282CHC82": {
            "id": "US91282CHC82",
            "name": "T 3 3/8 05/15/33",
            "shares": 3637000,
            "amount": 106745228,
            "weight": 9.0388,
            "price": 29.35
        },
        "US91282CGM73": {
            "id": "US91282CGM73",
            "name": "T 3 1/2 02/15/33",
            "shares": 3534000,
            "amount": 104893538,
            "weight": 8.882,
            "price": 29.68
        },
        "US91282CFV81": {
            "id": "US91282CFV81",
            "name": "T 4 1/8 11/15/32",
            "shares": 3346000,
            "amount": 104212927,
            "weight": 8.8244,
            "price": 31.15
        },
        "US91282CEP23": {
            "id": "US91282CEP23",
            "name": "T 2 7/8 05/15/32",
            "shares": 3331000,
            "amount": 94831150,
            "weight": 8.03,
            "price": 28.47
        },
        "US91282CFF32": {
            "id": "US91282CFF32",
            "name": "T 2 3/4 08/15/32",
            "shares": 3286000,
            "amount": 92395871,
            "weight": 7.8237,
            "price": 28.12
        },
        "US91282CDJ71": {
            "id": "US91282CDJ71",
            "name": "T 1 3/8 11/15/31",
            "shares": 3527000,
            "amount": 90256552,
            "weight": 7.6426,
            "price": 25.59
        },
        "US91282CDY49": {
            "id": "US91282CDY49",
            "name": "T 1 7/8 02/15/32",
            "shares": 3393000,
            "amount": 89815207,
            "weight": 7.6052,
            "price": 26.47
        },
        "US91282CCS89": {
            "id": "US91282CCS89",
            "name": "T 1 1/4 08/15/31",
            "shares": 3479000,
            "amount": 88804519,
            "weight": 7.5196,
            "price": 25.53
        },
        "US91282CJZ59": {
            "id": "US91282CJZ59",
            "name": "T 4 02/15/34",
            "shares": 2800000,
            "amount": 86279414,
            "weight": 7.3058,
            "price": 30.81
        },
        "US91282CCB54": {
            "id": "US91282CCB54",
            "name": "T 1 5/8 05/15/31",
            "shares": 3193000,
            "amount": 84347286,
            "weight": 7.1422,
            "price": 26.42
        }
    },
    "deposit": 3542738,
    "cash": 4124911
}